pyconcepticon/__init__.py
pyconcepticon/__main__.py
pyconcepticon/api.py
pyconcepticon/cli_util.py
pyconcepticon/conceptlist-metadata.json
pyconcepticon/glosses.py
pyconcepticon/models.py
pyconcepticon/test_util.py
pyconcepticon/util.py
pyconcepticon/commands/__init__.py
pyconcepticon/commands/attributes.py
pyconcepticon/commands/check.py
pyconcepticon/commands/citation.py
pyconcepticon/commands/create_metadata.py
pyconcepticon/commands/dump.py
pyconcepticon/commands/graph.py
pyconcepticon/commands/link.py
pyconcepticon/commands/lookup.py
pyconcepticon/commands/make_app.py
pyconcepticon/commands/make_linkdata.py
pyconcepticon/commands/map_concepts.py
pyconcepticon/commands/mergers.py
pyconcepticon/commands/notlinked.py
pyconcepticon/commands/recreate_networks.py
pyconcepticon/commands/rename.py
pyconcepticon/commands/shrink.py
pyconcepticon/commands/stats.py
pyconcepticon/commands/test.py
pyconcepticon/commands/upload_sources.py
pyconcepticon/commands/validate.py
pyconcepticon/test_repos/CONTRIBUTORS.md
pyconcepticon/test_repos/metadata.json
pyconcepticon/test_repos/concepticondata/concepticon.json
pyconcepticon/test_repos/concepticondata/concepticon.tsv
pyconcepticon/test_repos/concepticondata/conceptlists.tsv
pyconcepticon/test_repos/concepticondata/conceptrelations.tsv
pyconcepticon/test_repos/concepticondata/retired.json
pyconcepticon/test_repos/concepticondata/conceptlists/List-2023-1308.tsv
pyconcepticon/test_repos/concepticondata/conceptlists/Perrin-2010-110.tsv
pyconcepticon/test_repos/concepticondata/conceptlists/Sun-1991-1004.tsv
pyconcepticon/test_repos/concepticondata/conceptlists/default-metadata.json
pyconcepticon/test_repos/concepticondata/conceptlists/Sun-1991-1004/convert.py
pyconcepticon/test_repos/concepticondata/references/references.bib
pyconcepticon/test_repos/concepticondata/sources/cdstar.json
pyconcepticon/test_repos/mappings/map-en.tsv
pyconcepticon-3.1.0.dist-info/LICENSE
pyconcepticon-3.1.0.dist-info/METADATA
pyconcepticon-3.1.0.dist-info/WHEEL
pyconcepticon-3.1.0.dist-info/entry_points.txt
pyconcepticon-3.1.0.dist-info/top_level.txt
pyconcepticon-3.1.0.dist-info/RECORD
